{
    "id":  "war_scraps",
    "baseChancePct":  40.0,
    "entries":  [
                    {
                        "itemId":  "broken_plate",
                        "category":  "COMMON_SELL",
                        "chancePct":  16,
                        "minQty":  1,
                        "maxQty":  2,
                        "minRarity":  "COMMON",
                        "maxRarity":  "COMMON"
                    },
                    {
                        "itemId":  "damaged_gear",
                        "category":  "COMMON_SELL",
                        "chancePct":  14,
                        "minQty":  1,
                        "maxQty":  3,
                        "minRarity":  "COMMON",
                        "maxRarity":  "COMMON"
                    },
                    {
                        "itemId":  "bent_insignia",
                        "category":  "COMMON_SELL",
                        "chancePct":  12,
                        "minQty":  1,
                        "maxQty":  2,
                        "minRarity":  "COMMON",
                        "maxRarity":  "COMMON"
                    },
                    {
                        "itemId":  "worn_glove",
                        "category":  "COMMON_SELL",
                        "chancePct":  10,
                        "minQty":  1,
                        "maxQty":  2,
                        "minRarity":  "COMMON",
                        "maxRarity":  "COMMON"
                    },
                    {
                        "itemId":  "rough_hide",
                        "category":  "COMMON_MATERIAL",
                        "chancePct":  10,
                        "minQty":  1,
                        "maxQty":  2,
                        "minRarity":  "COMMON",
                        "maxRarity":  "COMMON"
                    },
                    {
                        "itemId":  "cracked_bone",
                        "category":  "COMMON_MATERIAL",
                        "chancePct":  8,
                        "minQty":  1,
                        "maxQty":  2,
                        "minRarity":  "COMMON",
                        "maxRarity":  "COMMON"
                    },
                    {
                        "itemId":  "rusted_coin",
                        "category":  "QUEST_ITEM",
                        "chancePct":  3,
                        "minQty":  2,
                        "maxQty":  5,
                        "minRarity":  "COMMON",
                        "maxRarity":  "COMMON"
                    },
                    {
                        "itemId":  "potion_small",
                        "category":  "CONSUMABLE",
                        "chancePct":  5,
                        "minQty":  1,
                        "maxQty":  1,
                        "minRarity":  "COMMON",
                        "maxRarity":  "COMMON"
                    },
                    {
                        "itemId":  "ether_small",
                        "category":  "CONSUMABLE",
                        "chancePct":  4,
                        "minQty":  1,
                        "maxQty":  1,
                        "minRarity":  "COMMON",
                        "maxRarity":  "COMMON"
                    },
                    {
                        "itemId":  "rusty_sword",
                        "category":  "EQUIPMENT_DROP",
                        "chancePct":  2,
                        "minQty":  1,
                        "maxQty":  1,
                        "minRarity":  "COMMON",
                        "maxRarity":  "RARE"
                    },
                    {
                        "templateIds":  [
                                            "wooden_shield",
                                            "iron_sword"
                                        ],
                        "category":  "EQUIPMENT_DROP",
                        "chancePct":  3,
                        "minQty":  1,
                        "maxQty":  1,
                        "minRarity":  "COMMON",
                        "maxRarity":  "RARE"
                    },
                    {
                        "templateIds":  [
                                            "warrior_guardblade",
                                            "warrior_guard_shield",
                                            "barbarian_raider_axe"
                                        ],
                        "category":  "EQUIPMENT_DROP",
                        "chancePct":  4,
                        "minQty":  1,
                        "maxQty":  1,
                        "minRarity":  "UNCOMMON",
                        "maxRarity":  "EPIC",
                        "minMonsterLevel":  20
                    },
                    {
                        "templateIds":  [
                                            "paladin_sunblade",
                                            "paladin_aegis_shield",
                                            "elite_guard_bastion_blade",
                                            "elite_guard_wall_shield",
                                            "berserker_frenzy_axe"
                                        ],
                        "category":  "EQUIPMENT_DROP",
                        "chancePct":  2,
                        "minQty":  1,
                        "maxQty":  1,
                        "minRarity":  "RARE",
                        "maxRarity":  "LEGENDARY",
                        "minMonsterLevel":  45
                    },
                    {
                        "templateIds":  [
                                            "bastion_sigil",
                                            "mercenary_token",
                                            "warded_loop"
                                        ],
                        "category":  "EQUIPMENT_DROP",
                        "chancePct":  2,
                        "minQty":  1,
                        "maxQty":  1,
                        "minRarity":  "UNCOMMON",
                        "maxRarity":  "EPIC"
                    },
                    {
                        "itemId":  "runic_core",
                        "category":  "RARE_COMPONENT",
                        "chancePct":  1,
                        "minQty":  1,
                        "maxQty":  1,
                        "minRarity":  "RARE",
                        "maxRarity":  "EPIC"
                    },
                    {
                        "templateIds":  [
                                            "s_warrior_helm_template",
                                            "s_warrior_chest_template",
                                            "s_warrior_gloves_template",
                                            "s_warrior_legs_template",
                                            "s_warrior_boots_template",
                                            "s_barbarian_helm_template",
                                            "s_barbarian_chest_template",
                                            "s_barbarian_gloves_template",
                                            "s_barbarian_legs_template",
                                            "s_barbarian_boots_template"
                                        ],
                        "category":  "EQUIPMENT_DROP",
                        "chancePct":  3,
                        "minQty":  1,
                        "maxQty":  1,
                        "minRarity":  "UNCOMMON",
                        "maxRarity":  "EPIC",
                        "minMonsterLevel":  20,
                        "minMapDropTier":  2,
                        "maxMapDropTier":  4
                    },
                    {
                        "templateIds":  [
                                            "s_warrior_paladin_helm_template",
                                            "s_warrior_paladin_chest_template",
                                            "s_warrior_paladin_gloves_template",
                                            "s_warrior_paladin_legs_template",
                                            "s_warrior_paladin_boots_template",
                                            "s_warrior_elite_guard_helm_template",
                                            "s_warrior_elite_guard_chest_template",
                                            "s_warrior_elite_guard_gloves_template",
                                            "s_warrior_elite_guard_legs_template",
                                            "s_warrior_elite_guard_boots_template",
                                            "s_barbarian_predator_helm_template",
                                            "s_barbarian_predator_chest_template",
                                            "s_barbarian_predator_gloves_template",
                                            "s_barbarian_predator_legs_template",
                                            "s_barbarian_predator_boots_template",
                                            "s_barbarian_berserker_helm_template",
                                            "s_barbarian_berserker_chest_template",
                                            "s_barbarian_berserker_gloves_template",
                                            "s_barbarian_berserker_legs_template",
                                            "s_barbarian_berserker_boots_template"
                                        ],
                        "category":  "EQUIPMENT_DROP",
                        "chancePct":  1.8,
                        "minQty":  1,
                        "maxQty":  1,
                        "minRarity":  "RARE",
                        "maxRarity":  "LEGENDARY",
                        "minMonsterLevel":  45,
                        "minMapDropTier":  4
                    }
                ]
}
